tree_sitter_markdown/__init__.py
tree_sitter_markdown/__init__.pyi
tree_sitter_markdown/_binding.abi3.so
tree_sitter_markdown/binding.c
tree_sitter_markdown/py.typed
tree_sitter_markdown/queries/markdown/highlights.scm
tree_sitter_markdown/queries/markdown/injections.scm
tree_sitter_markdown/queries/markdown_inline/highlights.scm
tree_sitter_markdown/queries/markdown_inline/injections.scm
tree_sitter_markdown-0.5.1.dist-info/METADATA
tree_sitter_markdown-0.5.1.dist-info/WHEEL
tree_sitter_markdown-0.5.1.dist-info/top_level.txt
tree_sitter_markdown-0.5.1.dist-info/RECORD
tree_sitter_markdown-0.5.1.dist-info/licenses/LICENSE
