Metadata-Version: 2.4
Name: tree-sitter-markdown
Version: 0.5.1
Summary: Markdown grammar for tree-sitter
Author: MDeiml
License: MIT
Project-URL: Homepage, https://github.com/tree-sitter-grammars/tree-sitter-markdown
Keywords: incremental,parsing,tree-sitter,markdown
Classifier: Intended Audience :: Developers
Classifier: License :: OSI Approved :: MIT License
Classifier: Topic :: Software Development :: Compilers
Classifier: Topic :: Text Processing :: Linguistic
Classifier: Typing :: Typed
Requires-Python: >=3.9
License-File: LICENSE
Provides-Extra: core
Requires-Dist: tree-sitter~=0.23; extra == "core"
Dynamic: license-file
